crudantic/__init__.py
crudantic/providers/__init__.py
crudantic/providers/logging/structlog/__init__.py
crudantic/providers/logging/structlog/provider.py
crudantic/providers/persistence/__init__.py
crudantic/providers/persistence/gcp_datastore/__init__.py
crudantic/providers/persistence/gcp_datastore/persistable.py
crudantic/providers/persistence/persistable.py
crudantic-0.0.23.dist-info/LICENSE
crudantic-0.0.23.dist-info/METADATA
crudantic-0.0.23.dist-info/WHEEL
crudantic-0.0.23.dist-info/RECORD
