Metadata-Version: 2.1
Name: crudantic
Version: 0.0.23
Summary: Quick and easy persistence for Pydantic models supporting basic CRUD operations
Author: David
Author-email: dbernstein613@gmail.com
Requires-Python: >=3.11,<4.0
Classifier: Programming Language :: Python :: 3
Classifier: Programming Language :: Python :: 3.11
Requires-Dist: better-exceptions (>=0.3.3,<0.4.0)
Requires-Dist: dependency-injector (>=4.41.0,<5.0.0)
Requires-Dist: google-cloud-datastore (>=2.18.0,<3.0.0)
Requires-Dist: invoke (>=2.2.0,<3.0.0)
Requires-Dist: orjson (>=3.9.10,<4.0.0)
Requires-Dist: pydantic (>=2.4.2,<3.0.0)
Requires-Dist: pydash (>=7.0.6,<8.0.0)
Requires-Dist: python-dotenv (>=1.0.0,<2.0.0)
Requires-Dist: rich (>=13.6.0,<14.0.0)
Requires-Dist: structlog (>=23.2.0,<24.0.0)
